README.md
setup.py
src/vdk/plugin/greenplum/greenplum_connection.py
src/vdk/plugin/greenplum/greenplum_plugin.py
src/vdk/plugin/greenplum/ingest_to_greenplum.py
src/vdk_greenplum.egg-info/PKG-INFO
src/vdk_greenplum.egg-info/SOURCES.txt
src/vdk_greenplum.egg-info/dependency_links.txt
src/vdk_greenplum.egg-info/entry_points.txt
src/vdk_greenplum.egg-info/requires.txt
src/vdk_greenplum.egg-info/top_level.txt
tests/test_ingest_to_greenplum.py
tests/test_vdk_greenplum_utils.py